mdiskpro/__init__.py
mdiskpro/main.py
mdiskpro-0.0.13.dist-info/LICENSE
mdiskpro-0.0.13.dist-info/METADATA
mdiskpro-0.0.13.dist-info/WHEEL
mdiskpro-0.0.13.dist-info/top_level.txt
mdiskpro-0.0.13.dist-info/RECORD
