Metadata-Version: 2.1
Name: mdiskpro
Version: 0.0.13
Summary: An Unofficial Mdiskpro.xyz API
Home-page: https://github.com/DKBOTZNETWORK
Author: DK BOTZ
Author-email: dkbotzhelp@gmail.com
License: MIT
Keywords: python,mdiskpro,gplink,url-shortener,earn money,shareus
Classifier: Development Status :: 1 - Planning
Classifier: Intended Audience :: Developers
Classifier: Programming Language :: Python :: 3
Classifier: Operating System :: Unix
Classifier: Operating System :: MacOS :: MacOS X
Classifier: Operating System :: Microsoft :: Windows
License-File: LICENSE
Requires-Dist: aiohttp
